README.txt
buildout.cfg
setup.py
bootstrap/bootstrap.py
docs/HISTORY.txt
z3c/__init__.py
z3c.persistentfactory.egg-info/PKG-INFO
z3c.persistentfactory.egg-info/SOURCES.txt
z3c.persistentfactory.egg-info/dependency_links.txt
z3c.persistentfactory.egg-info/entry_points.txt
z3c.persistentfactory.egg-info/namespace_packages.txt
z3c.persistentfactory.egg-info/not-zip-safe
z3c.persistentfactory.egg-info/requires.txt
z3c.persistentfactory.egg-info/top_level.txt
z3c/persistentfactory/README.txt
z3c/persistentfactory/__init__.py
z3c/persistentfactory/declarations.py
z3c/persistentfactory/declarations.txt
z3c/persistentfactory/factory.py
z3c/persistentfactory/factory.txt
z3c/persistentfactory/testing.py
z3c/persistentfactory/tests.py