Metadata-Version: 1.0
Name: z3c.persistentfactory
Version: 0.2
Summary: Wrap instance methods in persistent factory wrappers for using instance methods as ZCA factories.
Home-page: http://pypi.python.org/pypi/z3c.persistentfactory
Author: Ross Patterson
Author-email: me@rpatterson.net
License: ZPL
Platform: UNKNOWN
Classifier: Programming Language :: Python
Classifier: Topic :: Software Development :: Libraries :: Python Modules
